<?xml version="1.0" encoding="UTF-8"?><sem:triples xmlns:sem="http://marklogic.com/semantics"><sem:triple><sem:subject>http://schema.semantic-web.at/ppx/fullText/446760d9-2367-4cd7-9ca4-19d8b17dc496</sem:subject><sem:predicate>http://vocabulary.worldbank.org/taxonomy/134</sem:predicate><sem:object>http://vocabulary.worldbank.org/taxonomy/1843</sem:object></sem:triple><sem:triple><sem:subject>http://schema.semantic-web.at/ppx/fullText/446760d9-2367-4cd7-9ca4-19d8b17dc496</sem:subject><sem:predicate>http://vocabulary.worldbank.org/taxonomy/1920</sem:predicate><sem:object>http://localhost/importingexcel/509</sem:object></sem:triple><sem:triple><sem:subject>http://schema.semantic-web.at/ppx/fullText/446760d9-2367-4cd7-9ca4-19d8b17dc496</sem:subject><sem:predicate>http://vocabulary.worldbank.org/taxonomy/1921</sem:predicate><sem:object>http://localhost/importingexcel/509</sem:object></sem:triple><sem:triple><sem:subject>http://schema.semantic-web.at/ppx/fullText/446760d9-2367-4cd7-9ca4-19d8b17dc496</sem:subject><sem:predicate>http://vocabulary.worldbank.org/taxonomy/435</sem:predicate><sem:object>http://vocabulary.worldbank.org/taxonomy/170</sem:object></sem:triple><sem:triple><sem:subject>http://schema.semantic-web.at/ppx/fullText/446760d9-2367-4cd7-9ca4-19d8b17dc496</sem:subject><sem:predicate>http://vocabulary.worldbank.org/taxonomy/435</sem:predicate><sem:object>http://vocabulary.worldbank.org/taxonomy/199</sem:object></sem:triple><sem:triple><sem:subject>http://schema.semantic-web.at/ppx/fullText/446760d9-2367-4cd7-9ca4-19d8b17dc496</sem:subject><sem:predicate>http://vocabulary.worldbank.org/taxonomy/435</sem:predicate><sem:object>http://vocabulary.worldbank.org/taxonomy/174</sem:object></sem:triple><sem:triple><sem:subject>http://schema.semantic-web.at/ppx/fullText/446760d9-2367-4cd7-9ca4-19d8b17dc496</sem:subject><sem:predicate>http://vocabulary.worldbank.org/taxonomy/435</sem:predicate><sem:object>http://vocabulary.worldbank.org/taxonomy/178</sem:object></sem:triple><sem:triple><sem:subject>http://schema.semantic-web.at/ppx/fullText/446760d9-2367-4cd7-9ca4-19d8b17dc496</sem:subject><sem:predicate>http://vocabulary.worldbank.org/taxonomy/435</sem:predicate><sem:object>http://localhost/importingexcel/701</sem:object></sem:triple><sem:triple><sem:subject>http://schema.semantic-web.at/ppx/fullText/446760d9-2367-4cd7-9ca4-19d8b17dc496</sem:subject><sem:predicate>http://vocabulary.worldbank.org/taxonomy/435</sem:predicate><sem:object>http://vocabulary.worldbank.org/taxonomy/175</sem:object></sem:triple><sem:triple><sem:subject>http://schema.semantic-web.at/ppx/fullText/446760d9-2367-4cd7-9ca4-19d8b17dc496</sem:subject><sem:predicate>http://vocabulary.worldbank.org/taxonomy/435</sem:predicate><sem:object>http://vocabulary.worldbank.org/taxonomy/177</sem:object></sem:triple><sem:triple><sem:subject>http://schema.semantic-web.at/ppx/fullText/446760d9-2367-4cd7-9ca4-19d8b17dc496</sem:subject><sem:predicate>http://vocabulary.worldbank.org/taxonomy/471</sem:predicate><sem:object>http://vocabulary.worldbank.org/taxonomy/863</sem:object></sem:triple><sem:triple><sem:subject>http://schema.semantic-web.at/ppx/fullText/446760d9-2367-4cd7-9ca4-19d8b17dc496</sem:subject><sem:predicate>http://vocabulary.worldbank.org/taxonomy/566</sem:predicate><sem:object>http://vocabulary.worldbank.org/taxonomy/178</sem:object></sem:triple><sem:triple><sem:subject>http://schema.semantic-web.at/ppx/fullText/446760d9-2367-4cd7-9ca4-19d8b17dc496</sem:subject><sem:predicate>http://vocabulary.worldbank.org/taxonomy/621</sem:predicate><sem:object>http://vocabulary.worldbank.org/taxonomy/644</sem:object></sem:triple><sem:triple><sem:subject>http://schema.semantic-web.at/ppx/fullText/446760d9-2367-4cd7-9ca4-19d8b17dc496</sem:subject><sem:predicate>http://vocabulary.worldbank.org/taxonomy/621</sem:predicate><sem:object>http://vocabulary.worldbank.org/taxonomy/640</sem:object></sem:triple><sem:triple><sem:subject>http://schema.semantic-web.at/ppx/fullText/446760d9-2367-4cd7-9ca4-19d8b17dc496</sem:subject><sem:predicate>http://vocabulary.worldbank.org/taxonomy/621</sem:predicate><sem:object>http://vocabulary.worldbank.org/taxonomy/199</sem:object></sem:triple><sem:triple><sem:subject>http://schema.semantic-web.at/ppx/fullText/446760d9-2367-4cd7-9ca4-19d8b17dc496</sem:subject><sem:predicate>http://vocabulary.worldbank.org/taxonomy/695</sem:predicate><sem:object>http://localhost/importingexcel/418</sem:object></sem:triple><sem:triple><sem:subject>http://schema.semantic-web.at/ppx/fullText/446760d9-2367-4cd7-9ca4-19d8b17dc496</sem:subject><sem:predicate>http://vocabulary.worldbank.org/taxonomy/695</sem:predicate><sem:object>http://localhost/importingexcel/8</sem:object></sem:triple><sem:triple><sem:subject>http://schema.semantic-web.at/ppx/fullText/446760d9-2367-4cd7-9ca4-19d8b17dc496</sem:subject><sem:predicate>http://vocabulary.worldbank.org/taxonomy/696</sem:predicate><sem:object>http://vocabulary.worldbank.org/taxonomy/727</sem:object></sem:triple><sem:triple><sem:subject>http://schema.semantic-web.at/ppx/fullText/446760d9-2367-4cd7-9ca4-19d8b17dc496</sem:subject><sem:predicate>http://vocabulary.worldbank.org/taxonomy/696</sem:predicate><sem:object>http://vocabulary.worldbank.org/taxonomy/1040</sem:object></sem:triple><sem:triple><sem:subject>http://schema.semantic-web.at/ppx/fullText/446760d9-2367-4cd7-9ca4-19d8b17dc496</sem:subject><sem:predicate>http://vocabulary.worldbank.org/taxonomy/696</sem:predicate><sem:object>http://vocabulary.worldbank.org/taxonomy/1028</sem:object></sem:triple><sem:triple><sem:subject>http://schema.semantic-web.at/ppx/fullText/446760d9-2367-4cd7-9ca4-19d8b17dc496</sem:subject><sem:predicate>http://vocabulary.worldbank.org/taxonomy/697</sem:predicate><sem:object>http://vocabulary.worldbank.org/taxonomy/727</sem:object></sem:triple><sem:triple><sem:subject>http://schema.semantic-web.at/ppx/fullText/446760d9-2367-4cd7-9ca4-19d8b17dc496</sem:subject><sem:predicate>http://vocabulary.worldbank.org/taxonomy/697</sem:predicate><sem:object>http://localhost/importingexcel/289</sem:object></sem:triple><sem:triple><sem:subject>http://schema.semantic-web.at/ppx/teratopic/cfae9cd0-c372-41c6-984b-a9684556c026</sem:subject><sem:predicate>http://vocabulary.worldbank.org/taxonomy/1921</sem:predicate><sem:object>http://vocabulary.worldbank.org/taxonomy/1920</sem:object></sem:triple><sem:triple><sem:subject>http://schema.semantic-web.at/ppx/fullText/9d6bfee0-2de0-484f-984f-27096496acd0</sem:subject><sem:predicate>http://vocabulary.worldbank.org/taxonomy/470</sem:predicate><sem:object>http://vocabulary.worldbank.org/taxonomy/1512</sem:object></sem:triple><sem:triple><sem:subject>http://schema.semantic-web.at/ppx/fullText/003013db-764c-42c3-9d16-56ef4ddd01a4</sem:subject><sem:predicate>http://vocabulary.worldbank.org/taxonomy/698</sem:predicate><sem:object>http://vocabulary.worldbank.org/taxonomy/783</sem:object></sem:triple><sem:triple><sem:subject>http://schema.semantic-web.at/ppx/fullText/003013db-764c-42c3-9d16-56ef4ddd01a4</sem:subject><sem:predicate>http://vocabulary.worldbank.org/taxonomy/1920</sem:predicate><sem:object>http://vocabulary.worldbank.org/taxonomy/2031</sem:object></sem:triple><sem:triple><sem:subject>http://schema.semantic-web.at/ppx/fullText/003013db-764c-42c3-9d16-56ef4ddd01a4</sem:subject><sem:predicate>http://vocabulary.worldbank.org/taxonomy/1920</sem:predicate><sem:object>http://localhost/importingexcel/509</sem:object></sem:triple><sem:triple><sem:subject>http://schema.semantic-web.at/ppx/fullText/003013db-764c-42c3-9d16-56ef4ddd01a4</sem:subject><sem:predicate>http://vocabulary.worldbank.org/taxonomy/1920</sem:predicate><sem:object>http://vocabulary.worldbank.org/taxonomy/317</sem:object></sem:triple><sem:triple><sem:subject>http://schema.semantic-web.at/ppx/fullText/003013db-764c-42c3-9d16-56ef4ddd01a4</sem:subject><sem:predicate>http://vocabulary.worldbank.org/taxonomy/1921</sem:predicate><sem:object>http://vocabulary.worldbank.org/taxonomy/2031</sem:object></sem:triple><sem:triple><sem:subject>http://schema.semantic-web.at/ppx/fullText/003013db-764c-42c3-9d16-56ef4ddd01a4</sem:subject><sem:predicate>http://vocabulary.worldbank.org/taxonomy/1921</sem:predicate><sem:object>http://localhost/importingexcel/509</sem:object></sem:triple><sem:triple><sem:subject>http://schema.semantic-web.at/ppx/fullText/003013db-764c-42c3-9d16-56ef4ddd01a4</sem:subject><sem:predicate>http://vocabulary.worldbank.org/taxonomy/1921</sem:predicate><sem:object>http://vocabulary.worldbank.org/taxonomy/317</sem:object></sem:triple><sem:triple><sem:subject>http://schema.semantic-web.at/ppx/fullText/003013db-764c-42c3-9d16-56ef4ddd01a4</sem:subject><sem:predicate>http://vocabulary.worldbank.org/taxonomy/621</sem:predicate><sem:object>http://vocabulary.worldbank.org/taxonomy/1441</sem:object></sem:triple><sem:triple><sem:subject>http://schema.semantic-web.at/ppx/fullText/003013db-764c-42c3-9d16-56ef4ddd01a4</sem:subject><sem:predicate>http://vocabulary.worldbank.org/taxonomy/696</sem:predicate><sem:object>http://vocabulary.worldbank.org/taxonomy/2065</sem:object></sem:triple><sem:triple><sem:subject>http://schema.semantic-web.at/ppx/fullText/003013db-764c-42c3-9d16-56ef4ddd01a4</sem:subject><sem:predicate>http://vocabulary.worldbank.org/taxonomy/696</sem:predicate><sem:object>http://vocabulary.worldbank.org/taxonomy/2031</sem:object></sem:triple><sem:triple><sem:subject>http://schema.semantic-web.at/ppx/fullText/003013db-764c-42c3-9d16-56ef4ddd01a4</sem:subject><sem:predicate>http://vocabulary.worldbank.org/taxonomy/696</sem:predicate><sem:object>http://vocabulary.worldbank.org/taxonomy/843</sem:object></sem:triple><sem:triple><sem:subject>http://schema.semantic-web.at/ppx/fullText/003013db-764c-42c3-9d16-56ef4ddd01a4</sem:subject><sem:predicate>http://vocabulary.worldbank.org/taxonomy/696</sem:predicate><sem:object>http://vocabulary.worldbank.org/taxonomy/1026</sem:object></sem:triple><sem:triple><sem:subject>http://schema.semantic-web.at/ppx/fullText/003013db-764c-42c3-9d16-56ef4ddd01a4</sem:subject><sem:predicate>http://vocabulary.worldbank.org/taxonomy/697</sem:predicate><sem:object>http://localhost/importingexcel/289</sem:object></sem:triple><sem:triple><sem:subject>http://schema.semantic-web.at/ppx/fullText/d17102de-eeb3-4dd1-aa2c-872de3065798</sem:subject><sem:predicate>http://vocabulary.worldbank.org/taxonomy/699</sem:predicate><sem:object>http://vocabulary.worldbank.org/taxonomy/2529</sem:object></sem:triple><sem:triple><sem:subject>http://schema.semantic-web.at/ppx/fullText/d17102de-eeb3-4dd1-aa2c-872de3065798</sem:subject><sem:predicate>http://vocabulary.worldbank.org/taxonomy/1920</sem:predicate><sem:object>http://localhost/importingexcel/509</sem:object></sem:triple><sem:triple><sem:subject>http://schema.semantic-web.at/ppx/fullText/d17102de-eeb3-4dd1-aa2c-872de3065798</sem:subject><sem:predicate>http://vocabulary.worldbank.org/taxonomy/1921</sem:predicate><sem:object>http://localhost/importingexcel/509</sem:object></sem:triple><sem:triple><sem:subject>http://schema.semantic-web.at/ppx/fullText/d17102de-eeb3-4dd1-aa2c-872de3065798</sem:subject><sem:predicate>http://vocabulary.worldbank.org/taxonomy/2432</sem:predicate><sem:object>http://vocabulary.worldbank.org/taxonomy/2203</sem:object></sem:triple><sem:triple><sem:subject>http://schema.semantic-web.at/ppx/fullText/d17102de-eeb3-4dd1-aa2c-872de3065798</sem:subject><sem:predicate>http://vocabulary.worldbank.org/taxonomy/435</sem:predicate><sem:object>http://vocabulary.worldbank.org/taxonomy/337</sem:object></sem:triple><sem:triple><sem:subject>http://schema.semantic-web.at/ppx/fullText/d17102de-eeb3-4dd1-aa2c-872de3065798</sem:subject><sem:predicate>http://vocabulary.worldbank.org/taxonomy/621</sem:predicate><sem:object>http://vocabulary.worldbank.org/taxonomy/1305</sem:object></sem:triple><sem:triple><sem:subject>http://schema.semantic-web.at/ppx/fullText/d17102de-eeb3-4dd1-aa2c-872de3065798</sem:subject><sem:predicate>http://vocabulary.worldbank.org/taxonomy/621</sem:predicate><sem:object>http://vocabulary.worldbank.org/taxonomy/1406</sem:object></sem:triple><sem:triple><sem:subject>http://schema.semantic-web.at/ppx/fullText/d17102de-eeb3-4dd1-aa2c-872de3065798</sem:subject><sem:predicate>http://vocabulary.worldbank.org/taxonomy/621</sem:predicate><sem:object>http://vocabulary.worldbank.org/taxonomy/1448</sem:object></sem:triple><sem:triple><sem:subject>http://schema.semantic-web.at/ppx/fullText/d17102de-eeb3-4dd1-aa2c-872de3065798</sem:subject><sem:predicate>http://vocabulary.worldbank.org/taxonomy/621</sem:predicate><sem:object>http://vocabulary.worldbank.org/taxonomy/635</sem:object></sem:triple><sem:triple><sem:subject>http://schema.semantic-web.at/ppx/fullText/d17102de-eeb3-4dd1-aa2c-872de3065798</sem:subject><sem:predicate>http://vocabulary.worldbank.org/taxonomy/621</sem:predicate><sem:object>http://vocabulary.worldbank.org/taxonomy/1287</sem:object></sem:triple><sem:triple><sem:subject>http://schema.semantic-web.at/ppx/fullText/d17102de-eeb3-4dd1-aa2c-872de3065798</sem:subject><sem:predicate>http://vocabulary.worldbank.org/taxonomy/621</sem:predicate><sem:object>http://vocabulary.worldbank.org/taxonomy/640</sem:object></sem:triple><sem:triple><sem:subject>http://schema.semantic-web.at/ppx/fullText/d17102de-eeb3-4dd1-aa2c-872de3065798</sem:subject><sem:predicate>http://vocabulary.worldbank.org/taxonomy/621</sem:predicate><sem:object>http://vocabulary.worldbank.org/taxonomy/643</sem:object></sem:triple><sem:triple><sem:subject>http://schema.semantic-web.at/ppx/fullText/d17102de-eeb3-4dd1-aa2c-872de3065798</sem:subject><sem:predicate>http://vocabulary.worldbank.org/taxonomy/621</sem:predicate><sem:object>http://vocabulary.worldbank.org/taxonomy/1291</sem:object></sem:triple><sem:triple><sem:subject>http://schema.semantic-web.at/ppx/fullText/d17102de-eeb3-4dd1-aa2c-872de3065798</sem:subject><sem:predicate>http://vocabulary.worldbank.org/taxonomy/695</sem:predicate><sem:object>http://vocabulary.worldbank.org/taxonomy/1948</sem:object></sem:triple><sem:triple><sem:subject>http://schema.semantic-web.at/ppx/fullText/d17102de-eeb3-4dd1-aa2c-872de3065798</sem:subject><sem:predicate>http://vocabulary.worldbank.org/taxonomy/696</sem:predicate><sem:object>http://vocabulary.worldbank.org/taxonomy/726</sem:object></sem:triple><sem:triple><sem:subject>http://schema.semantic-web.at/ppx/fullText/d17102de-eeb3-4dd1-aa2c-872de3065798</sem:subject><sem:predicate>http://vocabulary.worldbank.org/taxonomy/696</sem:predicate><sem:object>http://localhost/importingexcel/663</sem:object></sem:triple><sem:triple><sem:subject>http://schema.semantic-web.at/ppx/fullText/d17102de-eeb3-4dd1-aa2c-872de3065798</sem:subject><sem:predicate>http://vocabulary.worldbank.org/taxonomy/696</sem:predicate><sem:object>http://vocabulary.worldbank.org/taxonomy/727</sem:object></sem:triple><sem:triple><sem:subject>http://schema.semantic-web.at/ppx/fullText/d17102de-eeb3-4dd1-aa2c-872de3065798</sem:subject><sem:predicate>http://vocabulary.worldbank.org/taxonomy/696</sem:predicate><sem:object>http://vocabulary.worldbank.org/taxonomy/832</sem:object></sem:triple><sem:triple><sem:subject>http://schema.semantic-web.at/ppx/fullText/d17102de-eeb3-4dd1-aa2c-872de3065798</sem:subject><sem:predicate>http://vocabulary.worldbank.org/taxonomy/696</sem:predicate><sem:object>http://vocabulary.worldbank.org/taxonomy/1014</sem:object></sem:triple><sem:triple><sem:subject>http://schema.semantic-web.at/ppx/fullText/d17102de-eeb3-4dd1-aa2c-872de3065798</sem:subject><sem:predicate>http://vocabulary.worldbank.org/taxonomy/696</sem:predicate><sem:object>http://vocabulary.worldbank.org/taxonomy/2025</sem:object></sem:triple><sem:triple><sem:subject>http://schema.semantic-web.at/ppx/fullText/d17102de-eeb3-4dd1-aa2c-872de3065798</sem:subject><sem:predicate>http://vocabulary.worldbank.org/taxonomy/696</sem:predicate><sem:object>http://vocabulary.worldbank.org/taxonomy/2026</sem:object></sem:triple><sem:triple><sem:subject>http://schema.semantic-web.at/ppx/fullText/d17102de-eeb3-4dd1-aa2c-872de3065798</sem:subject><sem:predicate>http://vocabulary.worldbank.org/taxonomy/697</sem:predicate><sem:object>http://vocabulary.worldbank.org/taxonomy/727</sem:object></sem:triple><sem:triple><sem:subject>http://schema.semantic-web.at/ppx/fullText/d17102de-eeb3-4dd1-aa2c-872de3065798</sem:subject><sem:predicate>http://vocabulary.worldbank.org/taxonomy/697</sem:predicate><sem:object>http://localhost/importingexcel/289</sem:object></sem:triple><sem:triple><sem:subject>http://schema.semantic-web.at/ppx/fullText/d17102de-eeb3-4dd1-aa2c-872de3065798</sem:subject><sem:predicate>http://vocabulary.worldbank.org/taxonomy/697</sem:predicate><sem:object>http://vocabulary.worldbank.org/taxonomy/1620</sem:object></sem:triple><sem:triple><sem:subject>http://schema.semantic-web.at/ppx/fullText/17b1fb39-85fc-4840-a4da-2690ad5f1f38</sem:subject><sem:predicate>http://vocabulary.worldbank.org/taxonomy/698</sem:predicate><sem:object>http://localhost/importingexcel/285</sem:object></sem:triple><sem:triple><sem:subject>http://schema.semantic-web.at/ppx/fullText/17b1fb39-85fc-4840-a4da-2690ad5f1f38</sem:subject><sem:predicate>http://localhost/importingexcel/703</sem:predicate><sem:object>http://localhost/importingexcel/453</sem:object></sem:triple><sem:triple><sem:subject>http://schema.semantic-web.at/ppx/fullText/17b1fb39-85fc-4840-a4da-2690ad5f1f38</sem:subject><sem:predicate>http://vocabulary.worldbank.org/taxonomy/1104</sem:predicate><sem:object>http://vocabulary.worldbank.org/taxonomy/450</sem:object></sem:triple><sem:triple><sem:subject>http://schema.semantic-web.at/ppx/fullText/17b1fb39-85fc-4840-a4da-2690ad5f1f38</sem:subject><sem:predicate>http://vocabulary.worldbank.org/taxonomy/137</sem:predicate><sem:object>http://vocabulary.worldbank.org/taxonomy/148</sem:object></sem:triple><sem:triple><sem:subject>http://schema.semantic-web.at/ppx/fullText/17b1fb39-85fc-4840-a4da-2690ad5f1f38</sem:subject><sem:predicate>http://vocabulary.worldbank.org/taxonomy/1920</sem:predicate><sem:object>http://vocabulary.worldbank.org/taxonomy/612</sem:object></sem:triple><sem:triple><sem:subject>http://schema.semantic-web.at/ppx/fullText/17b1fb39-85fc-4840-a4da-2690ad5f1f38</sem:subject><sem:predicate>http://vocabulary.worldbank.org/taxonomy/1920</sem:predicate><sem:object>http://localhost/importingexcel/509</sem:object></sem:triple><sem:triple><sem:subject>http://schema.semantic-web.at/ppx/fullText/17b1fb39-85fc-4840-a4da-2690ad5f1f38</sem:subject><sem:predicate>http://vocabulary.worldbank.org/taxonomy/1921</sem:predicate><sem:object>http://vocabulary.worldbank.org/taxonomy/612</sem:object></sem:triple><sem:triple><sem:subject>http://schema.semantic-web.at/ppx/fullText/17b1fb39-85fc-4840-a4da-2690ad5f1f38</sem:subject><sem:predicate>http://vocabulary.worldbank.org/taxonomy/1921</sem:predicate><sem:object>http://vocabulary.worldbank.org/taxonomy/846</sem:object></sem:triple><sem:triple><sem:subject>http://schema.semantic-web.at/ppx/fullText/17b1fb39-85fc-4840-a4da-2690ad5f1f38</sem:subject><sem:predicate>http://vocabulary.worldbank.org/taxonomy/1921</sem:predicate><sem:object>http://localhost/importingexcel/509</sem:object></sem:triple><sem:triple><sem:subject>http://schema.semantic-web.at/ppx/fullText/17b1fb39-85fc-4840-a4da-2690ad5f1f38</sem:subject><sem:predicate>http://vocabulary.worldbank.org/taxonomy/1921</sem:predicate><sem:object>http://vocabulary.worldbank.org/taxonomy/1277</sem:object></sem:triple><sem:triple><sem:subject>http://schema.semantic-web.at/ppx/fullText/17b1fb39-85fc-4840-a4da-2690ad5f1f38</sem:subject><sem:predicate>http://vocabulary.worldbank.org/taxonomy/1921</sem:predicate><sem:object>http://vocabulary.worldbank.org/taxonomy/1278</sem:object></sem:triple><sem:triple><sem:subject>http://schema.semantic-web.at/ppx/fullText/17b1fb39-85fc-4840-a4da-2690ad5f1f38</sem:subject><sem:predicate>http://vocabulary.worldbank.org/taxonomy/435</sem:predicate><sem:object>http://vocabulary.worldbank.org/taxonomy/337</sem:object></sem:triple><sem:triple><sem:subject>http://schema.semantic-web.at/ppx/fullText/17b1fb39-85fc-4840-a4da-2690ad5f1f38</sem:subject><sem:predicate>http://vocabulary.worldbank.org/taxonomy/435</sem:predicate><sem:object>http://localhost/importingexcel/364</sem:object></sem:triple><sem:triple><sem:subject>http://schema.semantic-web.at/ppx/fullText/17b1fb39-85fc-4840-a4da-2690ad5f1f38</sem:subject><sem:predicate>http://vocabulary.worldbank.org/taxonomy/435</sem:predicate><sem:object>http://vocabulary.worldbank.org/taxonomy/1951</sem:object></sem:triple><sem:triple><sem:subject>http://schema.semantic-web.at/ppx/fullText/17b1fb39-85fc-4840-a4da-2690ad5f1f38</sem:subject><sem:predicate>http://vocabulary.worldbank.org/taxonomy/439</sem:predicate><sem:object>http://vocabulary.worldbank.org/taxonomy/1132</sem:object></sem:triple><sem:triple><sem:subject>http://schema.semantic-web.at/ppx/fullText/17b1fb39-85fc-4840-a4da-2690ad5f1f38</sem:subject><sem:predicate>http://vocabulary.worldbank.org/taxonomy/566</sem:predicate><sem:object>http://vocabulary.worldbank.org/taxonomy/148</sem:object></sem:triple><sem:triple><sem:subject>http://schema.semantic-web.at/ppx/fullText/17b1fb39-85fc-4840-a4da-2690ad5f1f38</sem:subject><sem:predicate>http://vocabulary.worldbank.org/taxonomy/566</sem:predicate><sem:object>http://vocabulary.worldbank.org/taxonomy/2201</sem:object></sem:triple><sem:triple><sem:subject>http://schema.semantic-web.at/ppx/fullText/17b1fb39-85fc-4840-a4da-2690ad5f1f38</sem:subject><sem:predicate>http://vocabulary.worldbank.org/taxonomy/621</sem:predicate><sem:object>http://vocabulary.worldbank.org/taxonomy/640</sem:object></sem:triple><sem:triple><sem:subject>http://schema.semantic-web.at/ppx/fullText/17b1fb39-85fc-4840-a4da-2690ad5f1f38</sem:subject><sem:predicate>http://vocabulary.worldbank.org/taxonomy/696</sem:predicate><sem:object>http://vocabulary.worldbank.org/taxonomy/831</sem:object></sem:triple><sem:triple><sem:subject>http://schema.semantic-web.at/ppx/fullText/17b1fb39-85fc-4840-a4da-2690ad5f1f38</sem:subject><sem:predicate>http://vocabulary.worldbank.org/taxonomy/696</sem:predicate><sem:object>http://vocabulary.worldbank.org/taxonomy/727</sem:object></sem:triple><sem:triple><sem:subject>http://schema.semantic-web.at/ppx/fullText/17b1fb39-85fc-4840-a4da-2690ad5f1f38</sem:subject><sem:predicate>http://vocabulary.worldbank.org/taxonomy/696</sem:predicate><sem:object>http://vocabulary.worldbank.org/taxonomy/2528</sem:object></sem:triple><sem:triple><sem:subject>http://schema.semantic-web.at/ppx/fullText/17b1fb39-85fc-4840-a4da-2690ad5f1f38</sem:subject><sem:predicate>http://vocabulary.worldbank.org/taxonomy/696</sem:predicate><sem:object>http://vocabulary.worldbank.org/taxonomy/846</sem:object></sem:triple><sem:triple><sem:subject>http://schema.semantic-web.at/ppx/fullText/17b1fb39-85fc-4840-a4da-2690ad5f1f38</sem:subject><sem:predicate>http://vocabulary.worldbank.org/taxonomy/696</sem:predicate><sem:object>http://vocabulary.worldbank.org/taxonomy/1028</sem:object></sem:triple><sem:triple><sem:subject>http://schema.semantic-web.at/ppx/fullText/17b1fb39-85fc-4840-a4da-2690ad5f1f38</sem:subject><sem:predicate>http://vocabulary.worldbank.org/taxonomy/697</sem:predicate><sem:object>http://vocabulary.worldbank.org/taxonomy/727</sem:object></sem:triple><sem:triple><sem:subject>http://schema.semantic-web.at/ppx/fullText/17b1fb39-85fc-4840-a4da-2690ad5f1f38</sem:subject><sem:predicate>http://vocabulary.worldbank.org/taxonomy/697</sem:predicate><sem:object>http://localhost/importingexcel/289</sem:object></sem:triple><sem:triple><sem:subject>http://schema.semantic-web.at/ppx/fullText/4aa636de-f8d9-46f7-953e-2cb3e878001c</sem:subject><sem:predicate>http://vocabulary.worldbank.org/taxonomy/698</sem:predicate><sem:object>http://vocabulary.worldbank.org/taxonomy/776</sem:object></sem:triple><sem:triple><sem:subject>http://schema.semantic-web.at/ppx/fullText/4aa636de-f8d9-46f7-953e-2cb3e878001c</sem:subject><sem:predicate>http://vocabulary.worldbank.org/taxonomy/699</sem:predicate><sem:object>http://vocabulary.worldbank.org/taxonomy/2529</sem:object></sem:triple><sem:triple><sem:subject>http://schema.semantic-web.at/ppx/fullText/4aa636de-f8d9-46f7-953e-2cb3e878001c</sem:subject><sem:predicate>http://vocabulary.worldbank.org/taxonomy/699</sem:predicate><sem:object>http://vocabulary.worldbank.org/taxonomy/874</sem:object></sem:triple><sem:triple><sem:subject>http://schema.semantic-web.at/ppx/fullText/4aa636de-f8d9-46f7-953e-2cb3e878001c</sem:subject><sem:predicate>http://vocabulary.worldbank.org/taxonomy/133</sem:predicate><sem:object>http://vocabulary.worldbank.org/taxonomy/693</sem:object></sem:triple><sem:triple><sem:subject>http://schema.semantic-web.at/ppx/fullText/4aa636de-f8d9-46f7-953e-2cb3e878001c</sem:subject><sem:predicate>http://vocabulary.worldbank.org/taxonomy/1920</sem:predicate><sem:object>http://localhost/importingexcel/509</sem:object></sem:triple><sem:triple><sem:subject>http://schema.semantic-web.at/ppx/fullText/4aa636de-f8d9-46f7-953e-2cb3e878001c</sem:subject><sem:predicate>http://vocabulary.worldbank.org/taxonomy/1921</sem:predicate><sem:object>http://localhost/importingexcel/509</sem:object></sem:triple><sem:triple><sem:subject>http://schema.semantic-web.at/ppx/fullText/4aa636de-f8d9-46f7-953e-2cb3e878001c</sem:subject><sem:predicate>http://vocabulary.worldbank.org/taxonomy/1921</sem:predicate><sem:object>http://localhost/importingexcel/356</sem:object></sem:triple><sem:triple><sem:subject>http://schema.semantic-web.at/ppx/fullText/4aa636de-f8d9-46f7-953e-2cb3e878001c</sem:subject><sem:predicate>http://vocabulary.worldbank.org/taxonomy/439</sem:predicate><sem:object>http://vocabulary.worldbank.org/taxonomy/874</sem:object></sem:triple><sem:triple><sem:subject>http://schema.semantic-web.at/ppx/fullText/4aa636de-f8d9-46f7-953e-2cb3e878001c</sem:subject><sem:predicate>http://vocabulary.worldbank.org/taxonomy/470</sem:predicate><sem:object>http://vocabulary.worldbank.org/taxonomy/2142</sem:object></sem:triple><sem:triple><sem:subject>http://schema.semantic-web.at/ppx/fullText/4aa636de-f8d9-46f7-953e-2cb3e878001c</sem:subject><sem:predicate>http://vocabulary.worldbank.org/taxonomy/470</sem:predicate><sem:object>http://vocabulary.worldbank.org/taxonomy/2149</sem:object></sem:triple><sem:triple><sem:subject>http://schema.semantic-web.at/ppx/fullText/4aa636de-f8d9-46f7-953e-2cb3e878001c</sem:subject><sem:predicate>http://vocabulary.worldbank.org/taxonomy/471</sem:predicate><sem:object>http://vocabulary.worldbank.org/taxonomy/863</sem:object></sem:triple><sem:triple><sem:subject>http://schema.semantic-web.at/ppx/fullText/4aa636de-f8d9-46f7-953e-2cb3e878001c</sem:subject><sem:predicate>http://vocabulary.worldbank.org/taxonomy/471</sem:predicate><sem:object>http://vocabulary.worldbank.org/taxonomy/1079</sem:object></sem:triple><sem:triple><sem:subject>http://schema.semantic-web.at/ppx/fullText/4aa636de-f8d9-46f7-953e-2cb3e878001c</sem:subject><sem:predicate>http://vocabulary.worldbank.org/taxonomy/507</sem:predicate><sem:object>http://localhost/importingexcel/132</sem:object></sem:triple><sem:triple><sem:subject>http://schema.semantic-web.at/ppx/fullText/4aa636de-f8d9-46f7-953e-2cb3e878001c</sem:subject><sem:predicate>http://vocabulary.worldbank.org/taxonomy/566</sem:predicate><sem:object>http://vocabulary.worldbank.org/taxonomy/1791</sem:object></sem:triple></sem:triples>